s2fft/README.rst
s2fft/__init__.py
s2fft/_version.py
s2fft/base_transforms/__init__.py
s2fft/base_transforms/spherical.py
s2fft/base_transforms/wigner.py
s2fft/precompute_transforms/__init__.py
s2fft/precompute_transforms/construct.py
s2fft/precompute_transforms/custom_ops.py
s2fft/precompute_transforms/fourier_wigner.py
s2fft/precompute_transforms/spherical.py
s2fft/precompute_transforms/wigner.py
s2fft/recursions/__init__.py
s2fft/recursions/price_mcewen.py
s2fft/recursions/risbo.py
s2fft/recursions/risbo_jax.py
s2fft/recursions/trapani.py
s2fft/recursions/turok.py
s2fft/recursions/turok_jax.py
s2fft/sampling/__init__.py
s2fft/sampling/reindex.py
s2fft/sampling/s2_samples.py
s2fft/sampling/so3_samples.py
s2fft/transforms/__init__.py
s2fft/transforms/c_backend_spherical.py
s2fft/transforms/otf_recursions.py
s2fft/transforms/spherical.py
s2fft/transforms/wigner.py
s2fft/utils/__init__.py
s2fft/utils/healpix_ffts.py
s2fft/utils/iterative_refinement.py
s2fft/utils/jax_primitive.py
s2fft/utils/quadrature.py
s2fft/utils/quadrature_jax.py
s2fft/utils/quadrature_torch.py
s2fft/utils/resampling.py
s2fft/utils/resampling_jax.py
s2fft/utils/resampling_torch.py
s2fft/utils/rotation.py
s2fft/utils/signal_generator.py
s2fft/utils/torch_wrapper.py
s2fft_lib/_s2fft.pypy310-pp73-x86_64-linux-gnu.so
s2fft-1.3.0.dist-info/METADATA
s2fft-1.3.0.dist-info/WHEEL
s2fft-1.3.0.dist-info/RECORD
s2fft-1.3.0.dist-info/licenses/LICENCE.txt
