Metadata-Version: 2.1
Name: s2fft
Version: 1.3.0
Summary: Differentiable and accelerated spherical transforms with JAX
Author: Matthew A. Price, Jason D. McEwen, Contributors
License: MIT License
Classifier: Programming Language :: Python :: 3
Classifier: Programming Language :: Python :: 3 :: Only
Classifier: Programming Language :: Python :: 3.8
Classifier: Programming Language :: Python :: 3.9
Classifier: Programming Language :: Python :: 3.10
Classifier: Programming Language :: Python :: 3.11
Classifier: Programming Language :: Python :: 3.12
Classifier: Operating System :: OS Independent
Classifier: Intended Audience :: Developers
Classifier: Intended Audience :: Science/Research
Project-URL: homepage, https://github.com/astro-informatics/s2fft
Requires-Python: >=3.8
Requires-Dist: numpy>=1.20
Requires-Dist: jax<0.6.0,>=0.3.13
Requires-Dist: jaxlib
Provides-Extra: docs
Requires-Dist: sphinx>=5.0.0; extra == "docs"
Requires-Dist: nbsphinx-link>=1.3.0; extra == "docs"
Requires-Dist: pydata-sphinx-theme>=0.12.0; extra == "docs"
Requires-Dist: sphinx_toolbox>=2.15.0; extra == "docs"
Requires-Dist: sphinx-tabs>=3.2.0; extra == "docs"
Requires-Dist: sphinxcontrib-bibtex>=2.4.1; extra == "docs"
Requires-Dist: sphinx-git>=11.0.0; extra == "docs"
Requires-Dist: sphinxcontrib-texfigure>=0.1.3; extra == "docs"
Requires-Dist: sphinx-copybutton; extra == "docs"
Requires-Dist: sphinxemoji; extra == "docs"
Requires-Dist: sphinx_rtd_theme; extra == "docs"
Requires-Dist: sphinx_mdinclude; extra == "docs"
Requires-Dist: ipython>=7.16.1; extra == "docs"
Requires-Dist: jupyter>=1.0.0; extra == "docs"
Provides-Extra: plotting
Requires-Dist: pyvista; extra == "plotting"
Requires-Dist: trame; extra == "plotting"
Requires-Dist: ipykernel; extra == "plotting"
Requires-Dist: ipywidgets; extra == "plotting"
Provides-Extra: tests
Requires-Dist: ducc0; extra == "tests"
Requires-Dist: healpy; extra == "tests"
Requires-Dist: numpy<2; extra == "tests"
Requires-Dist: pytest; extra == "tests"
Requires-Dist: pytest-cov; extra == "tests"
Requires-Dist: so3; extra == "tests"
Requires-Dist: pyssht; extra == "tests"
Requires-Dist: torch; extra == "tests"
Provides-Extra: torch
Requires-Dist: torch; extra == "torch"
